setup.py
stackmob-parse-migrator
client/__init__.py
stackmob_parse_migrator.egg-info/PKG-INFO
stackmob_parse_migrator.egg-info/SOURCES.txt
stackmob_parse_migrator.egg-info/dependency_links.txt
stackmob_parse_migrator.egg-info/requires.txt
stackmob_parse_migrator.egg-info/top_level.txt
util/__init__.py