Metadata-Version: 1.0
Name: stackmob-parse-migrator
Version: 1.0.1
Summary: A script to add exported Parse data to StackMob
Home-page: http://github.com/stackmob/stackmob-parse-migrator
Author: Douglas Rapp
Author-email: support@stackmob.com
License: UNKNOWN
Platform: UNKNOWN
